MANIFEST.in
README.rst
setup.py
sphinxbootstrap4theme.py
sphinxbootstrap4theme.egg-info/PKG-INFO
sphinxbootstrap4theme.egg-info/SOURCES.txt
sphinxbootstrap4theme.egg-info/dependency_links.txt
sphinxbootstrap4theme.egg-info/top_level.txt
themes/sphinxbootstrap4theme/breadcrumb.html
themes/sphinxbootstrap4theme/footer.html
themes/sphinxbootstrap4theme/globaltoc.html
themes/sphinxbootstrap4theme/layout.html
themes/sphinxbootstrap4theme/navbar.html
themes/sphinxbootstrap4theme/navbarsearch.html
themes/sphinxbootstrap4theme/search.html
themes/sphinxbootstrap4theme/searchbox.html
themes/sphinxbootstrap4theme/sourcelink.html
themes/sphinxbootstrap4theme/theme.conf
themes/sphinxbootstrap4theme/static/sphinxbootstrap4.css_t
themes/sphinxbootstrap4theme/static/sphinxbootstrap4.js_t
themes/sphinxbootstrap4theme/static/bootstrap-4.3.1-dist/css/bootstrap-grid.min.css
themes/sphinxbootstrap4theme/static/bootstrap-4.3.1-dist/css/bootstrap-grid.min.css.map
themes/sphinxbootstrap4theme/static/bootstrap-4.3.1-dist/css/bootstrap-reboot.min.css
themes/sphinxbootstrap4theme/static/bootstrap-4.3.1-dist/css/bootstrap-reboot.min.css.map
themes/sphinxbootstrap4theme/static/bootstrap-4.3.1-dist/css/bootstrap.min.css
themes/sphinxbootstrap4theme/static/bootstrap-4.3.1-dist/css/bootstrap.min.css.map
themes/sphinxbootstrap4theme/static/bootstrap-4.3.1-dist/js/bootstrap.bundle.min.js
themes/sphinxbootstrap4theme/static/bootstrap-4.3.1-dist/js/bootstrap.bundle.min.js.map
themes/sphinxbootstrap4theme/static/bootstrap-4.3.1-dist/js/bootstrap.min.js
themes/sphinxbootstrap4theme/static/bootstrap-4.3.1-dist/js/bootstrap.min.js.map