Metadata-Version: 1.1
Name: sphinxbootstrap4theme
Version: 0.6.0
Summary: Sphinx Bootstrap4 Theme
Home-page: https://github.com/myyasuda/sphinxbootstrap4theme
Author: Masahiko Yasuda
Author-email: myasuda@uchida.co.jp
License: MIT License
Platform: UNKNOWN
Classifier: Development Status :: 5 - Production/Stable
Classifier: Environment :: Web Environment
Classifier: Intended Audience :: Developers
Classifier: Intended Audience :: System Administrators
Classifier: License :: OSI Approved :: MIT License
Classifier: Operating System :: OS Independent
Classifier: Programming Language :: Python
Classifier: Topic :: Internet
Classifier: Topic :: Software Development :: Documentation
